PyPunch/__init__.py
PyPunch/main.py
PyPunch/mappings.py
PyPunch/template_card.jpg
PyPunch-1.0.0.dist-info/LICENSE
PyPunch-1.0.0.dist-info/METADATA
PyPunch-1.0.0.dist-info/WHEEL
PyPunch-1.0.0.dist-info/top_level.txt
PyPunch-1.0.0.dist-info/RECORD
