Metadata-Version: 2.1
Name: PyPunch
Version: 1.0.0
Summary: A Punchcard generation package
Home-page: https://github.com/TheToddLuci0/PyPunch
Author: TheToddLuci0
License: BSD
Keywords: punchcard
Platform: UNKNOWN
Classifier: Programming Language :: Python :: 3
Classifier: License :: OSI Approved :: BSD License
Classifier: Operating System :: OS Independent
Classifier: Development Status :: 5 - Production/Stable
Requires-Python: >=3
Requires-Dist: pillow
